ecu/sbl/aace/datalake/__init__.py
ecu/sbl/aace/datalake/_version.py
ecu/sbl/aace/datalake/common.py
ecu_sbl_aace_datalake-0.1.14.dist-info/LICENSE
ecu_sbl_aace_datalake-0.1.14.dist-info/METADATA
ecu_sbl_aace_datalake-0.1.14.dist-info/WHEEL
ecu_sbl_aace_datalake-0.1.14.dist-info/top_level.txt
ecu_sbl_aace_datalake-0.1.14.dist-info/RECORD
