Metadata-Version: 2.1
Name: ecu_sbl_aace_datalake
Version: 0.1.14
Summary: Supporting utilities for the ECU SBL AACE Datalake project
Author-email: Jonathan Mills <support.sbl@itsalljustdata.com>
Maintainer-email: Jonathan Mills <support.sbl@itsalljustdata.com>
License: MIT
Project-URL: Homepage, https://github.com/itsalljustdata/ecu_sbl_aace_datalake
Project-URL: Bug Reports, https://github.com/itsalljustdata/ecu_sbl_aace_datalake/issues
Keywords: utilities
Classifier: Development Status :: 3 - Alpha
Classifier: Intended Audience :: Developers
Classifier: Topic :: Software Development :: Build Tools
Classifier: License :: OSI Approved :: MIT License
Classifier: Programming Language :: Python :: 3.11
Classifier: Programming Language :: Python :: 3.12
Classifier: Programming Language :: Python :: 3.13
Classifier: Programming Language :: Python :: 3 :: Only
Requires-Python: >=3.11.8
License-File: LICENSE
Provides-Extra: dev
Provides-Extra: test
